{
    "id": 3543219,
    "name": "Speed Racer",
    "author": "ZenthicAlpha",
    "creators": ["ZenthicAlpha"],
    "verifier": "Leo",
    "verification": "https://youtu.be/R8RsJVKKd8w?si=Wa2Xu6Ibjd7y5Zz7",
    "percentToQualify": "60",
    "password": "Free To Copy",
    "records": [
        {
            "user": "Aidan",
            "link": "linkplaceholder",
            "percent": 100,
            "hz": 60
        },
        {
            "user": "Connor",
            "link": "link",
            "percent": 100,
            "hz": 60
        },
        {
            "user": "Leo (School)",
            "link": "linkplaceholder",
            "percent": 100,
            "hz": 60
        }
    ]
}
