
{
    "id": 58002670,
    "name": "Iron God: Sakupen Hell Yes RMX",
    "author": "Sivlol",
    "creators": ["Skrypto", "Chuck", "Scopal", "GD Iris", "andhika"],
    "verifier": "Raghav",
    "verification": "https://youtu.be/QNm8ZsBINvk",
    "percentToQualify": "60",
    "password": "Free To Copy",
    "records": [
        {
            "user": "Ben",
            "link": "linkplaceholder",
            "percent": 100,
            "hz": 60
        },
        {
            "user": "Eli",
            "link": "linkplaceholder",
            "percent": 100,
            "hz": 240
        },
        {
            "user": "Est",
            "link": "linkplaceholder",
            "percent": 100,
            "hz": 240
        },
        {
            "user": "Leo",
            "link": "linkplaceholder",
            "percent": 100,
            "hz": 480
        } 
    ]
}
